Metadata-Version: 2.1
Name: test-random2
Version: 0.0.1
Summary: little module that helps to create tables for a specified schema with random content
Home-page: UNKNOWN
Author: detective (Maxim Perl)
Author-email: <Maxim.Perl@detective.solutions>
License: UNKNOWN
Keywords: python,pandas,numpy,tables,data,data science
Platform: UNKNOWN
Classifier: Development Status :: 1 - Planning
Classifier: Intended Audience :: Developers
Classifier: Programming Language :: Python :: 3
Classifier: Operating System :: Unix
Classifier: Operating System :: MacOS :: MacOS X
Classifier: Operating System :: Microsoft :: Windows
Requires-Dist: numpy
Requires-Dist: pandas
